pylint_aiida.py
pylint_aiida-0.1.1.dist-info/LICENSE
pylint_aiida-0.1.1.dist-info/WHEEL
pylint_aiida-0.1.1.dist-info/METADATA
pylint_aiida-0.1.1.dist-info/RECORD
